quake_sdk/__init__.py
quake_sdk/client.py
quake_sdk/exceptions.py
quake_sdk/models.py
quake_sdk_py-0.3.0.dist-info/licenses/LICENSE
quake_sdk_py-0.3.0.dist-info/METADATA
quake_sdk_py-0.3.0.dist-info/WHEEL
quake_sdk_py-0.3.0.dist-info/top_level.txt
quake_sdk_py-0.3.0.dist-info/RECORD
