Metadata-Version: 2.4
Name: quake-sdk-py
Version: 0.3.0
Summary: Python SDK for the Quake API (360.net)
Home-page: https://github.com/Explorer1092/quake_sdk/tree/main/quake_sdk_py
Author: Your Name
Author-email: your.email@example.com
Project-URL: Documentation, https://quake.360.net/quake/#/help?id=5f9f9b9b3b9b3b9b3b9b3b9b
Project-URL: Source, https://github.com/Explorer1092/quake_sdk/tree/main/quake_sdk_py
Project-URL: Tracker, https://github.com/Explorer1092/quake_sdk/issues
Keywords: quake 360 network-security api sdk pydantic
Classifier: Programming Language :: Python :: 3
Classifier: License :: OSI Approved :: MIT License
Classifier: Operating System :: OS Independent
Classifier: Development Status :: 3 - Alpha
Classifier: Intended Audience :: Developers
Classifier: Topic :: Security
Classifier: Topic :: Software Development :: Libraries :: Python Modules
Requires-Python: >=3.7
License-File: LICENSE
Requires-Dist: requests>=2.20.0
Requires-Dist: pydantic>=1.8.0
Dynamic: author
Dynamic: author-email
Dynamic: classifier
Dynamic: description
Dynamic: description-content-type
Dynamic: home-page
Dynamic: keywords
Dynamic: license-file
Dynamic: project-url
Dynamic: requires-dist
Dynamic: requires-python
Dynamic: summary
